spook/__init__.py
spook/apps.py
spook/exceptions.py
spook/pagination.py
spook/resources.py
spook/responses.py
spook/settings.py
spook/transformers.py
spook/utils.py
spook/validators.py
spook/views.py
spook-3.2.8.dist-info/LICENSE
spook-3.2.8.dist-info/WHEEL
spook-3.2.8.dist-info/METADATA
spook-3.2.8.dist-info/RECORD
