Metadata-Version: 2.1
Name: spook
Version: 3.2.8
Summary: Django Rest Framework library to interconnect external APIs
Home-page: https://github.com/pablo-moreno/spook
License: MIT
Keywords: http,api,microservices
Author: Pablo Moreno
Author-email: pablomoreno.inf@gmail.com
Requires-Python: >=3.7,<4
Classifier: Development Status :: 5 - Production/Stable
Classifier: Framework :: Django :: 2.2
Classifier: Framework :: Django :: 3.2
Classifier: License :: OSI Approved :: MIT License
Classifier: Programming Language :: Python :: 3
Classifier: Programming Language :: Python :: 3.7
Classifier: Programming Language :: Python :: 3.8
Classifier: Programming Language :: Python :: 3.9
Classifier: Topic :: Software Development :: Libraries :: Python Modules
Requires-Dist: coverage (>=5.3)
Requires-Dist: django (>=2.2.0)
Requires-Dist: djangorestframework (>=3.3.1)
Requires-Dist: djangorestframework-jwt (>=1.11.0)
Requires-Dist: requests (>=2.24.0)
